Enrichproqt/Enrichproqt.py
Enrichproqt/__init__.py
Enrichproqt/data/BP_pathway_dict.pkl
Enrichproqt/data/CC_pathway_dict.pkl
Enrichproqt/data/MF_pathway_dict.pkl
Enrichproqt-0.3.0.dist-info/METADATA
Enrichproqt-0.3.0.dist-info/WHEEL
Enrichproqt-0.3.0.dist-info/top_level.txt
Enrichproqt-0.3.0.dist-info/RECORD
