Metadata-Version: 2.1
Name: Enrichproqt
Version: 0.3.0
Summary: Pathway Enrichment Analysis for Protein Lists
Home-page: https://github.com/qinti2023/Enrichproqt
Author: qinti
Author-email: qinti@zju.edu.cn
Classifier: Programming Language :: Python :: 3
Classifier: License :: OSI Approved :: MIT License
Classifier: Operating System :: OS Independent
Requires-Python: >=3.6
Requires-Dist: numpy
Requires-Dist: scipy
Requires-Dist: pandas
Requires-Dist: statsmodels
